isitwo/__init__.py
isitwo/main.py
isitwo-0.1.0.dist-info/entry_points.txt
isitwo-0.1.0.dist-info/WHEEL
isitwo-0.1.0.dist-info/METADATA
isitwo-0.1.0.dist-info/RECORD
